mlbomdoc/__init__.py
mlbomdoc/cli.py
mlbomdoc/generator.py
mlbomdoc/version.py
mlbomdoc-0.1.1.dist-info/LICENSE
mlbomdoc-0.1.1.dist-info/METADATA
mlbomdoc-0.1.1.dist-info/WHEEL
mlbomdoc-0.1.1.dist-info/entry_points.txt
mlbomdoc-0.1.1.dist-info/top_level.txt
mlbomdoc-0.1.1.dist-info/RECORD
